[
  {
    "DayOfWeek": "Четверг",
    "StartTime": "14:00:00",
    "EndTime": "15:30:00",
    "WeekType": "Нижняя неделя",
    "Classroom": "Б 318",
    "Group": "1380",
    "Subject": "Гидромеханика",
    "InstructorName": "Ермолаева Елена Валерьевна",
    "InstructorLink": "https://www.smtu.ru/ru/viewperson/102673/"
  },
  {
    "DayOfWeek": "Пятница",
    "StartTime": "10:10:00",
    "EndTime": "11:40:00",
    "WeekType": "Верхняя неделя",
    "Classroom": "Б 318",
    "Group": "1220",
    "Subject": "Гидродинамика морских инженерных сооружений",
    "InstructorName": "Ермолаева Елена Валерьевна",
    "InstructorLink": "https://www.smtu.ru/ru/viewperson/102673/"
  },
  {
    "DayOfWeek": "Пятница",
    "StartTime": "10:10:00",
    "EndTime": "11:40:00",
    "WeekType": "Нижняя неделя",
    "Classroom": "Б 316",
    "Group": "1220",
    "Subject": "Гидродинамика морских инженерных сооружений",
    "InstructorName": "Ермолаева Елена Валерьевна",
    "InstructorLink": "https://www.smtu.ru/ru/viewperson/102673/"
  },
  {
    "DayOfWeek": "Суббота",
    "StartTime": "10:10:00",
    "EndTime": "11:40:00",
    "WeekType": "Верхняя неделя",
    "Classroom": "Б 102",
    "Group": "3220",
    "Subject": "Гидромеханика",
    "InstructorName": "Ермолаева Елена Валерьевна",
    "InstructorLink": "https://www.smtu.ru/ru/viewperson/102673/"
  },
  {
    "DayOfWeek": "Суббота",
    "StartTime": "11:50:00",
    "EndTime": "13:20:00",
    "WeekType": "Верхняя неделя",
    "Classroom": "Б 102",
    "Group": "3200",
    "Subject": "Гидромеханика",
    "InstructorName": "Ермолаева Елена Валерьевна",
    "InstructorLink": "https://www.smtu.ru/ru/viewperson/102673/"
  }
]