[
  {
    "DayOfWeek": "Понедельник",
    "StartTime": "2024-04-07T08:30:00",
    "EndTime": "2024-04-07T10:00:00",
    "WeekType": "Обе недели",
    "Classroom": "У 418",
    "Group": "8120",
    "Subject": "Русский язык",
    "InstructorName": "Рогова Татьяна Ивановна",
    "InstructorLink": ""
  },
  {
    "DayOfWeek": "Понедельник",
    "StartTime": "2024-04-07T10:10:00",
    "EndTime": "2024-04-07T11:40:00",
    "WeekType": "Обе недели",
    "Classroom": "У 418",
    "Group": "8160",
    "Subject": "Русский язык",
    "InstructorName": "Рогова Татьяна Ивановна",
    "InstructorLink": ""
  },
  {
    "DayOfWeek": "Понедельник",
    "StartTime": "2024-04-07T11:50:00",
    "EndTime": "2024-04-07T13:20:00",
    "WeekType": "Обе недели",
    "Classroom": "У 418",
    "Group": "8170",
    "Subject": "Русский язык",
    "InstructorName": "Рогова Татьяна Ивановна",
    "InstructorLink": ""
  },
  {
    "DayOfWeek": "Понедельник",
    "StartTime": "2024-04-07T14:00:00",
    "EndTime": "2024-04-07T15:30:00",
    "WeekType": "Обе недели",
    "Classroom": "У 418",
    "Group": "8130",
    "Subject": "Русский язык",
    "InstructorName": "Рогова Татьяна Ивановна",
    "InstructorLink": ""
  },
  {
    "DayOfWeek": "Вторник",
    "StartTime": "2024-04-07T08:30:00",
    "EndTime": "2024-04-07T10:00:00",
    "WeekType": "Обе недели",
    "Classroom": "У 418",
    "Group": "8150",
    "Subject": "Русский язык",
    "InstructorName": "Рогова Татьяна Ивановна",
    "InstructorLink": ""
  },
  {
    "DayOfWeek": "Вторник",
    "StartTime": "2024-04-07T10:10:00",
    "EndTime": "2024-04-07T11:40:00",
    "WeekType": "Обе недели",
    "Classroom": "У 418",
    "Group": "8140",
    "Subject": "Русский язык",
    "InstructorName": "Рогова Татьяна Ивановна",
    "InstructorLink": ""
  },
  {
    "DayOfWeek": "Вторник",
    "StartTime": "2024-04-07T11:50:00",
    "EndTime": "2024-04-07T13:20:00",
    "WeekType": "Обе недели",
    "Classroom": "У 418",
    "Group": "8110",
    "Subject": "Русский язык",
    "InstructorName": "Рогова Татьяна Ивановна",
    "InstructorLink": ""
  },
  {
    "DayOfWeek": "Вторник",
    "StartTime": "2024-04-07T14:00:00",
    "EndTime": "2024-04-07T15:30:00",
    "WeekType": "Нижняя неделя",
    "Classroom": "У 314",
    "Group": "8110",
    "Subject": "Час куратора",
    "InstructorName": "Рогова Татьяна Ивановна",
    "InstructorLink": ""
  },
  {
    "DayOfWeek": "Четверг",
    "StartTime": "2024-04-07T08:30:00",
    "EndTime": "2024-04-07T10:00:00",
    "WeekType": "Верхняя неделя",
    "Classroom": "У 421",
    "Group": "8120",
    "Subject": "Родная литература",
    "InstructorName": "Рогова Татьяна Ивановна",
    "InstructorLink": ""
  },
  {
    "DayOfWeek": "Четверг",
    "StartTime": "2024-04-07T10:10:00",
    "EndTime": "2024-04-07T11:40:00",
    "WeekType": "Верхняя неделя",
    "Classroom": "У 418",
    "Group": "8150",
    "Subject": "Родная литература",
    "InstructorName": "Рогова Татьяна Ивановна",
    "InstructorLink": ""
  },
  {
    "DayOfWeek": "Четверг",
    "StartTime": "2024-04-07T10:10:00",
    "EndTime": "2024-04-07T11:40:00",
    "WeekType": "Нижняя неделя",
    "Classroom": "У 418",
    "Group": "8170",
    "Subject": "Родная литература",
    "InstructorName": "Рогова Татьяна Ивановна",
    "InstructorLink": ""
  },
  {
    "DayOfWeek": "Четверг",
    "StartTime": "2024-04-07T11:50:00",
    "EndTime": "2024-04-07T13:20:00",
    "WeekType": "Верхняя неделя",
    "Classroom": "У 418",
    "Group": "8110",
    "Subject": "Родная литература",
    "InstructorName": "Рогова Татьяна Ивановна",
    "InstructorLink": ""
  },
  {
    "DayOfWeek": "Четверг",
    "StartTime": "2024-04-07T11:50:00",
    "EndTime": "2024-04-07T13:20:00",
    "WeekType": "Нижняя неделя",
    "Classroom": "У 418",
    "Group": "8160",
    "Subject": "Родная литература",
    "InstructorName": "Рогова Татьяна Ивановна",
    "InstructorLink": ""
  },
  {
    "DayOfWeek": "Четверг",
    "StartTime": "2024-04-07T14:00:00",
    "EndTime": "2024-04-07T15:30:00",
    "WeekType": "Верхняя неделя",
    "Classroom": "У 421",
    "Group": "8140",
    "Subject": "Родная литература",
    "InstructorName": "Рогова Татьяна Ивановна",
    "InstructorLink": ""
  },
  {
    "DayOfWeek": "Четверг",
    "StartTime": "2024-04-07T14:00:00",
    "EndTime": "2024-04-07T15:30:00",
    "WeekType": "Нижняя неделя",
    "Classroom": "У 420",
    "Group": "8130",
    "Subject": "Родная литература",
    "InstructorName": "Рогова Татьяна Ивановна",
    "InstructorLink": ""
  },
  {
    "DayOfWeek": "Пятница",
    "StartTime": "2024-04-07T10:10:00",
    "EndTime": "2024-04-07T11:40:00",
    "WeekType": "Нижняя неделя",
    "Classroom": "У 424",
    "Group": "8120",
    "Subject": "Час куратора",
    "InstructorName": "Рогова Татьяна Ивановна",
    "InstructorLink": ""
  }
]